ray_quickstart/__init__.py
ray_quickstart/init.py
ray_quickstart/monkey_patch.py
ray_quickstart/rsync_syncer.py
ray_quickstart/util/__init__.py
ray_quickstart/util/debug.py
ray_quickstart/util/platform.py
ray_quickstart-0.1.28.data/scripts/ray_start.bat
ray_quickstart-0.1.28.data/scripts/ray_start.sh
ray_quickstart-0.1.28.data/scripts/ray_stop.bat
ray_quickstart-0.1.28.data/scripts/ray_stop.sh
ray_quickstart-0.1.28.dist-info/LICENSE.txt
ray_quickstart-0.1.28.dist-info/METADATA
ray_quickstart-0.1.28.dist-info/WHEEL
ray_quickstart-0.1.28.dist-info/top_level.txt
ray_quickstart-0.1.28.dist-info/RECORD
