Metadata-Version: 2.1
Name: ray-quickstart
Version: 0.1.28
Summary: Wrapper around the Ray library to make it easier for you to set up your ML project to use Ray to train/tune your models remotely on a GPU-enabled computer
Author-email: Tuyen Truong <tuyen.truong@gmail.com>
Project-URL: Homepage, https://github.com/tuyentruong/ray_quickstart
Project-URL: Bug Tracker, https://github.com/tuyentruong/ray_quickstart/issues
Classifier: Development Status :: 3 - Alpha
Classifier: Intended Audience :: Developers
Classifier: License :: OSI Approved :: MIT License
Classifier: Operating System :: OS Independent
Classifier: Programming Language :: Python :: 3
Requires-Python: >=3.7
License-File: LICENSE.txt
Requires-Dist: ray
